toga_cocoa/__init__.py
toga_cocoa/app.py
toga_cocoa/colors.py
toga_cocoa/command.py
toga_cocoa/constraints.py
toga_cocoa/container.py
toga_cocoa/dialogs.py
toga_cocoa/factory.py
toga_cocoa/fonts.py
toga_cocoa/icons.py
toga_cocoa/images.py
toga_cocoa/keys.py
toga_cocoa/paths.py
toga_cocoa/screens.py
toga_cocoa/statusicons.py
toga_cocoa/window.py
toga_cocoa/hardware/__init__.py
toga_cocoa/hardware/camera.py
toga_cocoa/hardware/location.py
toga_cocoa/libs/__init__.py
toga_cocoa/libs/appkit.py
toga_cocoa/libs/av_foundation.py
toga_cocoa/libs/core_graphics.py
toga_cocoa/libs/core_location.py
toga_cocoa/libs/core_text.py
toga_cocoa/libs/foundation.py
toga_cocoa/libs/mapkit.py
toga_cocoa/libs/webkit.py
toga_cocoa/resources/camera.png
toga_cocoa/resources/toga.icns
toga_cocoa/widgets/__init__.py
toga_cocoa/widgets/activityindicator.py
toga_cocoa/widgets/base.py
toga_cocoa/widgets/box.py
toga_cocoa/widgets/button.py
toga_cocoa/widgets/canvas.py
toga_cocoa/widgets/detailedlist.py
toga_cocoa/widgets/divider.py
toga_cocoa/widgets/imageview.py
toga_cocoa/widgets/label.py
toga_cocoa/widgets/mapview.py
toga_cocoa/widgets/multilinetextinput.py
toga_cocoa/widgets/numberinput.py
toga_cocoa/widgets/optioncontainer.py
toga_cocoa/widgets/passwordinput.py
toga_cocoa/widgets/progressbar.py
toga_cocoa/widgets/scrollcontainer.py
toga_cocoa/widgets/selection.py
toga_cocoa/widgets/slider.py
toga_cocoa/widgets/splitcontainer.py
toga_cocoa/widgets/switch.py
toga_cocoa/widgets/table.py
toga_cocoa/widgets/textinput.py
toga_cocoa/widgets/tree.py
toga_cocoa/widgets/webview.py
toga_cocoa/widgets/internal/__init__.py
toga_cocoa/widgets/internal/cells.py
toga_cocoa/widgets/internal/data.py
toga_cocoa/widgets/internal/refresh.py
toga_cocoa-0.5.0.dist-info/LICENSE
toga_cocoa-0.5.0.dist-info/METADATA
toga_cocoa-0.5.0.dist-info/WHEEL
toga_cocoa-0.5.0.dist-info/entry_points.txt
toga_cocoa-0.5.0.dist-info/top_level.txt
toga_cocoa-0.5.0.dist-info/RECORD
